creepy_catacombs_s1/__init__.py
creepy_catacombs_s1/env/__init__.py
creepy_catacombs_s1/env/catacombs_env.py
creepy_catacombs_s1/map/__init__.py
creepy_catacombs_s1/map/generator.py
creepy_catacombs_s1/param/__init__.py
creepy_catacombs_s1/param/env_params.py
creepy_catacombs_s1/render/__init__.py
creepy_catacombs_s1/render/pygame_render.py
creepy_catacombs_s1/render/assets/agent.png
creepy_catacombs_s1/render/assets/floor.png
creepy_catacombs_s1/render/assets/goal.png
creepy_catacombs_s1/render/assets/ph.png
creepy_catacombs_s1/render/assets/start.png
creepy_catacombs_s1/render/assets/wall.png
creepy_catacombs_s1/render/assets/zombie.png
creepy_catacombs_s1-0.1.4.dist-info/licenses/LICENSE
creepy_catacombs_s1-0.1.4.dist-info/METADATA
creepy_catacombs_s1-0.1.4.dist-info/WHEEL
creepy_catacombs_s1-0.1.4.dist-info/top_level.txt
creepy_catacombs_s1-0.1.4.dist-info/RECORD
